ebt_flash_attention/__init__.py
ebt_flash_attention/ebt_attention.py
ebt_flash_attention/ebt_backward_kernel.py
ebt_flash_attention/ebt_forward_kernel.py
ebt_flash_attention/ebt_forward_tma_kernel.py
ebt_flash_attention-0.2.0.dist-info/METADATA
ebt_flash_attention-0.2.0.dist-info/WHEEL
ebt_flash_attention-0.2.0.dist-info/licenses/LICENSE
ebt_flash_attention-0.2.0.dist-info/RECORD
